skalchemy/__init__.py
skalchemy/__main__.py
skalchemy/mla.py
skalchemy/modules/module.py
skalchemy-0.0.0.dist-info/METADATA
skalchemy-0.0.0.dist-info/WHEEL
skalchemy-0.0.0.dist-info/entry_points.txt
skalchemy-0.0.0.dist-info/top_level.txt
skalchemy-0.0.0.dist-info/RECORD
