Metadata-Version: 2.1
Name: skalchemy
Version: 0.0.0
Summary: machine learning alchemy
Home-page: https://gitlab.com/krink/skalchemy
Author: Karl Rink
Author-email: karl@rink.us
License: UNKNOWN
Project-URL: Bug Tracker, https://gitlab.com/krink/skalchemy/issues
Platform: UNKNOWN
Classifier: Programming Language :: Python :: 3 :: Only
Classifier: License :: OSI Approved :: MIT License
Classifier: Operating System :: OS Independent
Classifier: Development Status :: 4 - Beta
Classifier: Intended Audience :: Developers
Classifier: Natural Language :: English
Requires-Python: >=3.6
Requires-Dist: scikit-learn
